dexblue/__init__.py
dexblue/dexblue.py
dexblue/config/clientMethods.json
dexblue/config/serverEvents.json
dexblue_api_python-0.1.0b4.dist-info/LICENSE
dexblue_api_python-0.1.0b4.dist-info/METADATA
dexblue_api_python-0.1.0b4.dist-info/WHEEL
dexblue_api_python-0.1.0b4.dist-info/top_level.txt
dexblue_api_python-0.1.0b4.dist-info/RECORD
