Metadata-Version: 2.1
Name: dexblue-api-python
Version: 0.1.0b4
Summary: dex.blue API wrapper for python
Home-page: https://github.com/dexdotblue/dexblue-api-py
Author: dex.blue
Author-email: tech@dex.blue
License: MIT
Platform: UNKNOWN
Classifier: Programming Language :: Python :: 3
Classifier: License :: OSI Approved :: MIT License
Classifier: Operating System :: OS Independent
Requires-Python: >=3.7
Requires-Dist: web3 (>=5.0.2)
Requires-Dist: websockets (>=7.0)
